trajan/__init__.py
trajan/cli.py
trajan/constants.py
trajan/utils.py
trajan/handlers/__init__.py
trajan/handlers/angle.py
trajan/handlers/base_handler.py
trajan/handlers/density.py
trajan/handlers/qunit.py
trajan/handlers/rdfs.py
trajan/handlers/rings.py
trajan/handlers/vdos.py
lammps_trajan-0.0.9.dist-info/METADATA
lammps_trajan-0.0.9.dist-info/WHEEL
lammps_trajan-0.0.9.dist-info/entry_points.txt
lammps_trajan-0.0.9.dist-info/licenses/LICENSE
lammps_trajan-0.0.9.dist-info/RECORD
