Metadata-Version: 2.4
Name: lammps-trajan
Version: 0.0.9
Summary: LAMMPS trajectory file analysis utility
Project-URL: Homepage, https://github.com/DuGroup-FGM2L/trajan
Project-URL: Source, https://github.com/superde1fin/trajan
Project-URL: Issues, https://github.com/superde1fin/trajan/issues
License: GPL-3.0-only
License-File: LICENSE
Requires-Python: >=3.6
Requires-Dist: importlib-metadata<6.7.0; python_version < '3.8'
Requires-Dist: numpy>=1.21.6
Requires-Dist: scipy>=1.7.3
Provides-Extra: dev
Requires-Dist: build>=1.2; extra == 'dev'
Requires-Dist: mypy>=1.10; extra == 'dev'
Requires-Dist: pytest>=8.1; extra == 'dev'
Requires-Dist: ruff>=0.4; extra == 'dev'
Requires-Dist: twine>=5.0; extra == 'dev'
